{
"type": "FeatureCollection",
"name": "geo_22_短期入所療養介護(療養病床を有する病院等）",
"crs": { "type": "name", "properties": { "name": "urn:ogc:def:crs:OGC:1.3:CRS84" } },
"features": [
{ "type": "Feature", "properties": { "緯度": 34.7370781, "経度": 137.6880636, "url": "https://www.kaigokensaku.mhlw.go.jp/22/index.php?action_kouhyou_detail_004_kani=true&JigyosyoCd=2217110549-00&ServiceCd=&Type=search", "url2": "http://www.nishiyama.or.jp/", "内容": "医療法人社団一穂会　西山病院【短期入所療養介護(療養病床を有する病院等）】静岡県浜松市西区西山町５００番地", "サービスの種類": "短期入所療養介護(療養病床を有する病院等）" }, "geometry": { "type": "Point", "coordinates": [ 137.6880636, 34.7370781 ] } },
{ "type": "Feature", "properties": { "緯度": 34.7459694, "経度": 137.7325928, "url": "https://www.kaigokensaku.mhlw.go.jp/22/index.php?action_kouhyou_detail_004_kani=true&JigyosyoCd=2217211057-00&ServiceCd=&Type=search", "url2": "http://www.sakanoue-fc.jp", "内容": "医療法人社団　心　坂の上在宅医療支援医院【短期入所療養介護(療養病床を有する病院等）】静岡県浜松市中央区幸4-36-2", "サービスの種類": "短期入所療養介護(療養病床を有する病院等）" }, "geometry": { "type": "Point", "coordinates": [ 137.7325928, 34.7459694 ] } }
]
}
